MANIFEST.in
README.rst
setup.py
FuncBrows/__init__.py
FuncBrows/funcbrows.py
FuncBrows/test.html
FuncBrows/test_funcbrows.py
FuncBrows.egg-info/PKG-INFO
FuncBrows.egg-info/SOURCES.txt
FuncBrows.egg-info/dependency_links.txt
FuncBrows.egg-info/not-zip-safe
FuncBrows.egg-info/requires.txt
FuncBrows.egg-info/top_level.txt