Metadata-Version: 1.0
Name: FuncBrows
Version: 0.1.7
Summary: Web functional testing abstraction layer
Home-page: http://pypi.python.org/pypi/funcbrows
Author: Tom Wardill
Author-email: tom.wardill@isotoma.com
License: BSD License
Keywords: functional test web browser
Platform: UNKNOWN
Classifier: Development Status :: 3 - Alpha
Classifier: Intended Audience :: Developers
Classifier: License :: OSI Approved :: BSD License
Classifier: Operating System :: POSIX
Classifier: Programming Language :: Python
